Workbook

Sheet Resumo
A2: Biblioteca de referências de UI | Pinterest
A4: Imagens distintas | B4: =COUNTA(Referencias!A2:A24523) -> 11236 | D4: Como usar
A5: Meta | B5: 10000 | D5: 1. Abra Referencias e filtre a macroárea.
A6: Progresso | B6: =B4/B5 -> 1.1236 | D6: 2. Abra o link da imagem ou da fonte.
A7: Pins com link individual | B7: 566 | D7: 3. Marque Sua seleção e Favorito.
A8: Páginas de origem | B8: 793 | D8: Categorias inferidas pelo contexto da fonte.
A9: Situação | B9: Coleta encerrada; imagens sendo enviadas ao GitHub | D9: A base ainda não recebeu curadoria visual.
D10: Imagem distinta não significa projeto distinto.
A12: Macroárea | B12: Imagens distintas | D12: =HYPERLINK("https://github.com/C-Icaro/ui-references-pinterest","Repositório privado: base e imagens") -> #ERROR!
A13: Alimentação e Delivery | B13: =COUNTIF(Referencias!B2:B24523,A13) -> 504
A14: Autenticação e Onboarding | B14: =COUNTIF(Referencias!B2:B24523,A14) -> 460
A15: CRM | B15: =COUNTIF(Referencias!B2:B24523,A15) -> 496
A16: Componentes | B16: =COUNTIF(Referencias!B2:B24523,A16) -> 561
A17: Dashboards e Analytics | B17: =COUNTIF(Referencias!B2:B24523,A17) -> 491
A18: E-commerce | B18: =COUNTIF(Referencias!B2:B24523,A18) -> 518
A19: Educação | B19: =COUNTIF(Referencias!B2:B24523,A19) -> 522
A20: Fintech e Bancos | B20: =COUNTIF(Referencias!B2:B24523,A20) -> 507
A21: IA e Chatbots | B21: =COUNTIF(Referencias!B2:B24523,A21) -> 161
A22: Landing Pages e Sites | B22: =COUNTIF(Referencias!B2:B24523,A22) -> 592
A23: Mapas e Mobilidade | B23: =COUNTIF(Referencias!B2:B24523,A23) -> 490
A24: Mobile | B24: =COUNTIF(Referencias!B2:B24523,A24) -> 567
A25: Mídia e Entretenimento | B25: =COUNTIF(Referencias!B2:B24523,A25) -> 516
A26: Produtividade e Gestão | B26: =COUNTIF(Referencias!B2:B24523,A26) -> 490
A27: Redes Sociais e Comunidades | B27: =COUNTIF(Referencias!B2:B24523,A27) -> 497
A28: Saúde e Bem-estar | B28: =COUNTIF(Referencias!B2:B24523,A28) -> 516
A29: Tipografia e Cores | B29: =COUNTIF(Referencias!B2:B24523,A29) -> 502
A30: UI 3D | B30: =COUNTIF(Referencias!B2:B24523,A30) -> 487
A31: UI e UX Geral | B31: =COUNTIF(Referencias!B2:B24523,A31) -> 1849
A32: Viagens e Reservas | B32: =COUNTIF(Referencias!B2:B24523,A32) -> 510

Sheet Referencias
A1: ID | B1: Macroárea | C1: Subcategoria | D1: Título disponível | E1: Link do pin | F1: Link da imagem | G1: Página de origem | H1: Nome da fonte | I1: Tipo de captura | J1: Revisão visual | K1: Coletado em (UTC) | L1: Assinatura da imagem | M1: Sua seleção | N1: Favorito | O1: Suas notas
A2: UI-00001 | B2: Alimentação e Delivery | C2: app design inspiration for food apps | D2: Título não exposto pela fonte | F2: https://i.pinimg.com/originals/c3/2b/31/c32b3179b9bce2fb4a85fbb5b63e9777.jpg | G2: https://www.pinterest.com/ideas/app-design-inspiration-for-food-apps/921185940841/ | H2: App Design Inspiration for Food Apps | I2: Página pública: imagem vinculada à coletânea/tópico | J2: Não revisado visualmente; categoria inferida pela fonte | K2: 2026-10-23T02:08:14Z | L2: c32b3179b9bce2fb4a85fbb5b63e9777 | M2: A avaliar | N2: Não
A3: UI-00002 | B3: Alimentação e Delivery | C3: app design inspiration for food apps | D3: Título não exposto pela fonte | F3: https://i.pinimg.com/originals/c7/2f/fe/c72ffe4adfede523cfef9fae2e66e164.jpg | G3: https://www.pinterest.com/ideas/app-design-inspiration-for-food-apps/921185940841/ | H3: App Design Inspiration for Food Apps | I3: Página pública: imagem vinculada à coletânea/tópico | J3: Não revisado visualmente; categoria inferida pela fonte | K3: 2026-10-23T02:08:14Z | L3: c72ffe4adfede523cfef9fae2e66e164 | M3: A avaliar | N3: Não
A4: UI-00003 | B4: Alimentação e Delivery | C4: app design inspiration for food apps | D4: Título não exposto pela fonte | F4: https://i.pinimg.com/originals/d1/43/85/d1438560d90258e612498699d8cbaeaa.gif | G4: https://www.pinterest.com/ideas/app-design-inspiration-for-food-apps/921185940841/ | H4: App Design Inspiration for Food Apps | I4: Página pública: imagem vinculada à coletânea/tópico | J4: Não revisado visualmente; categoria inferida pela fonte | K4: 2026-10-23T02:08:14Z | L4: d1438560d90258e612498699d8cbaeaa | M4: A avaliar | N4: Não
A5: UI-00004 | B5: Alimentação e Delivery | C5: app design inspiration for food apps | D5: Título não exposto pela fonte | F5: https://i.pinimg.com/originals/e9/ff/00/e9ff00951125dd0fa845f546a3e7c946.jpg | G5: https://www.pinterest.com/ideas/app-design-inspiration-for-food-apps/921185940841/ | H5: App Design Inspiration for Food Apps | I5: Página pública: imagem vinculada à coletânea/tópico | J5: Não revisado visualmente; categoria inferida pela fonte | K5: 2026-10-23T02:08:14Z | L5: e9ff00951125dd0fa845f546a3e7c946 | M5: A avaliar | N5: Não
A6: UI-00005 | B6: Alimentação e Delivery | C6: app design inspiration for food apps | D6: Título não exposto pela fonte | F6: https://i.pinimg.com/originals/f9/63/e5/f963e5085a68e781e21ca5852bfa0ec5.jpg | G6: https://www.pinterest.com/ideas/app-design-inspiration-for-food-apps/921185940841/ | H6: App Design Inspiration for Food Apps | I6: Página pública: imagem vinculada à coletânea/tópico | J6: Não revisado visualmente; categoria inferida pela fonte | K6: 2026-10-23T02:08:14Z | L6: f963e5085a68e781e21ca5852bfa0ec5 | M6: A avaliar | N6: Não
A7: UI-00006 | B7: Alimentação e Delivery | C7: best food website design | D7: Título não exposto pela fonte | F7: https://i.pinimg.com/originals/06/4e/06/064e06b3a65c60075704c6a70405a088.jpg | G7: https://www.pinterest.com/ideas/best-food-website-design/937630932982/ | H7: Best Food Website Design | I7: Página pública: imagem vinculada à coletânea/tópico | J7: Não revisado visualmente; categoria inferida pela fonte | K7: 2026-10-23T02:06:07Z | L7: 064e06b3a65c60075704c6a70405a088 | M7: A avaliar | N7: Não
A8: UI-00007 | B8: Alimentação e Delivery | C8: best food website design | D8: Título não exposto pela fonte | F8: https://i.pinimg.com/originals/11/69/c9/1169c95c97a17869c89386890108832f.jpg | G8: https://www.pinterest.com/ideas/best-food-website-design/937630932982/ | H8: Best Food Website Design | I8: Página pública: imagem vinculada à coletânea/tópico | J8: Não revisado visualmente; categoria inferida pela fonte | K8: 2026-10-23T02:06:07Z | L8: 1169c95c97a17869c89386890108832f | M8: A avaliar | N8: Não
A9: UI-00008 | B9: Alimentação e Delivery | C9: best food website design | D9: Título não exposto pela fonte | F9: https://i.pinimg.com/originals/11/ff/cf/11ffcff027e910c23ff708e96a83cb28.jpg | G9: https://www.pinterest.com/ideas/best-food-website-design/937630932982/ | H9: Best Food Website Design | I9: Página pública: imagem vinculada à coletânea/tópico | J9: Não revisado visualmente; categoria inferida pela fonte | K9: 2026-10-23T02:06:07Z | L9: 11ffcff027e910c23ff708e96a83cb28 | M9: A avaliar | N9: Não
A10: UI-00009 | B10: Alimentação e Delivery | C10: best food website design | D10: Título não exposto pela fonte | F10: https://i.pinimg.com/originals/14/35/01/143501d883b65aec96727b9b9200856b.jpg | G10: https://www.pinterest.com/ideas/best-food-website-design/937630932982/ | H10: Best Food Website Design | I10: Página pública: imagem vinculada à coletânea/tópico | J10: Não revisado visualmente; categoria inferida pela fonte | K10: 2026-10-23T02:06:07Z | L10: 143501d883b65aec96727b9b9200856b | M10: A avaliar | N10: Não
A11: UI-00010 | B11: Alimentação e Delivery | C11: best food website design | D11: Título não exposto pela fonte | F11: https://i.pinimg.com/originals/1f/2e/48/1f2e48a58106faebbd24833a93fd121e.png | G11: https://www.pinterest.com/ideas/best-food-website-design/937630932982/ | H11: Best Food Website Design | I11: Página pública: imagem vinculada à coletânea/tópico | J11: Não revisado visualmente; categoria inferida pela fonte | K11: 2026-10-23T02:06:07Z | L11: 1f2e48a58106faebbd24833a93fd121e | M11: A avaliar | N11: Não
A12: UI-00011 | B12: Alimentação e Delivery | C12: best food website design | D12: Título não exposto pela fonte | F12: https://i.pinimg.com/originals/2d/b3/ab/2db3abf45da8929c0c6650d6177b7e8f.jpg | G12: https://www.pinterest.com/ideas/best-food-website-design/937630932982/ | H12: Best Food Website Design | I12: Página pública: imagem vinculada à coletânea/tópico | J12: Não revisado visualmente; categoria inferida pela fonte | K12: 2026-10-23T02:06:07Z | L12: 2db3abf45da8929c0c6650d6177b7e8f | M12: A avaliar | N12: Não
A13: UI-00012 | B13: Alimentação e Delivery | C13: best food website design | D13: Título não exposto pela fonte | F13: https://i.pinimg.com/originals/2f/c6/4f/2fc64fc35f98082134ddaff58624405f.jpg | G13: https://www.pinterest.com/ideas/best-food-website-design/937630932982/ | H13: Best Food Website Design | I13: Página pública: imagem vinculada à coletânea/tópico | J13: Não revisado visualmente; categoria inferida pela fonte | K13: 2026-10-23T02:06:07Z | L13: 2fc64fc35f98082134ddaff58624405f | M13: A avaliar | N13: Não
... A232: UI-00231 | B232: Alimentação e Delivery | C232: food company website design | D232: Título não exposto pela fonte | F232: https://i.pinimg.com/originals/db/e4/66/dbe466212d05ec71c04d561d4788cf8e.png | G232: https://www.pinterest.com/ideas/food-company-website-design/912251939332/ | H232: Food Company Website Design | I232: Página pública: imagem vinculada à coletânea/tópico | J232: Não revisado visualmente; categoria inferida pela fonte | K232: 2026-10-23T02:06:25Z | L232: dbe466212d05ec71c04d561d4788cf8e | M232: A avaliar | N232: Não
A233: UI-00232 | B233: Alimentação e Delivery | C233: Food Ordering App Design | D233: Título não exposto pela fonte | F233: https://i.pinimg.com/originals/04/b9/0d/04b90d943870318058fb0db958930b72.jpg | G233: https://www.pinterest.com/PixelFlowUI/food-ordering-app-design/ | I233: Página pública: imagem vinculada à coletânea/tópico | J233: Não revisado visualmente; categoria inferida pela fonte | K233: 2026-10-23T02:07:06Z | L233: 04b90d943870318058fb0db958930b72 | M233: A avaliar | N233: Não
A234: UI-00233 | B234: Alimentação e Delivery | C234: Food Ordering App Design | D234: Título não exposto pela fonte | F234: https://i.pinimg.com/originals/0d/a0/30/0da030137c3a0940b15ac98f4b1887c4.png | G234: https://www.pinterest.com/PixelFlowUI/food-ordering-app-design/ | I234: Página pública: imagem vinculada à coletânea/tópico | J234: Não revisado visualmente; categoria inferida pela fonte | K234: 2026-10-23T02:07:06Z | L234: 0da030137c3a0940b15ac98f4b1887c4 | M234: A avaliar | N234: Não
A235: UI-00234 | B235: Alimentação e Delivery | C235: Food Ordering App Design | D235: Título não exposto pela fonte | F235: https://i.pinimg.com/originals/13/17/71/131771ab0a19a5caf39d6158b107f2aa.jpg | G235: https://www.pinterest.com/PixelFlowUI/food-ordering-app-design/ | I235: Página pública: imagem vinculada à coletânea/tópico | J235: Não revisado visualmente; categoria inferida pela fonte | K235: 2026-10-23T02:07:06Z | L235: 131771ab0a19a5caf39d6158b107f2aa | M235: A avaliar | N235: Não
A236: UI-00235 | B236: Alimentação e Delivery | C236: Food Ordering App Design | D236: Título não exposto pela fonte | F236: https://i.pinimg.com/originals/1b/a2/d2/1ba2d262cbe066c8ef0ff112ac3ce0c2.webp | G236: https://www.pinterest.com/PixelFlowUI/food-ordering-app-design/ | I236: Página pública: imagem vinculada à coletânea/tópico | J236: Não revisado visualmente; categoria inferida pela fonte | K236: 2026-10-23T02:07:06Z | L236: 1ba2d262cbe066c8ef0ff112ac3ce0c2 | M236: A avaliar | N236: Não
A237: UI-00236 | B237: Alimentação e Delivery | C237: Food Ordering App Design | D237: Título não exposto pela fonte | F237: https://i.pinimg.com/originals/39/09/40/390940e4416bb8e93b35fe5bbbadd1a4.jpg | G237: https://www.pinterest.com/PixelFlowUI/food-ordering-app-design/ | I237: Página pública: imagem vinculada à coletânea/tópico | J237: Não revisado visualmente; categoria inferida pela fonte | K237: 2026-10-23T02:07:06Z | L237: 390940e4416bb8e93b35fe5bbbadd1a4 | M237: A avaliar | N237: Não
A238: UI-00237 | B238: Alimentação e Delivery | C238: Food Ordering App Design | D238: Título não exposto pela fonte | F238: https://i.pinimg.com/originals/4b/16/1d/4b161d2b9dd39bffc6cc70808b74498e.jpg | G238: https://www.pinterest.com/PixelFlowUI/food-ordering-app-design/ | I238: Página pública: imagem vinculada à coletânea/tópico | J238: Não revisado visualmente; categoria inferida pela fonte | K238: 2026-10-23T02:07:06Z | L238: 4b161d2b9dd39bffc6cc70808b74498e | M238: A avaliar | N238: Não
A239: UI-00238 | B239: Alimentação e Delivery | C239: Food Ordering App Design | D239: Título não exposto pela fonte | F239: https://i.pinimg.com/originals/51/15/ee/5115ee8f41d25eedf3a16a467fb493b6.png | G239: https://www.pinterest.com/PixelFlowUI/food-ordering-app-design/ | I239: Página pública: imagem vinculada à coletânea/tópico | J239: Não revisado visualmente; categoria inferida pela fonte | K239: 2026-10-23T02:07:06Z | L239: 5115ee8f41d25eedf3a16a467fb493b6 | M239: A avaliar | N239: Não
A240: UI-00239 | B240: Alimentação e Delivery | C240: Food Ordering App Design | D240: Título não exposto pela fonte | F240: https://i.pinimg.com/originals/54/8b/4e/548b4e6c37a70fc1b2015d98b883a096.jpg | G240: https://www.pinterest.com/PixelFlowUI/food-ordering-app-design/ | I240: Página pública: imagem vinculada à coletânea/tópico | J240: Não revisado visualmente; categoria inferida pela fonte | K240: 2026-10-23T02:07:06Z | L240: 548b4e6c37a70fc1b2015d98b883a096 | M240: A avaliar | N240: Não
A241: UI-00240 | B241: Alimentação e Delivery | C241: Food Ordering App Design | D241: Título não exposto pela fonte | F241: https://i.pinimg.com/originals/69/04/07/6904071a5155e9d1126389c3614409ef.png | G241: https://www.pinterest.com/PixelFlowUI/food-ordering-app-design/ | I241: Página pública: imagem vinculada à coletânea/tópico | J241: Não revisado visualmente; categoria inferida pela fonte | K241: 2026-10-23T02:07:06Z | L241: 6904071a5155e9d1126389c3614409ef | M241: A avaliar | N241: Não
A242: UI-00241 | B242: Alimentação e Delivery | C242: Food Ordering App Design | D242: Título não exposto pela fonte | F242: https://i.pinimg.com/originals/69/bb/51/69bb511e1d0f58e14b563752441bd656.jpg | G242: https://www.pinterest.com/PixelFlowUI/food-ordering-app-design/ | I242: Página pública: imagem vinculada à coletânea/tópico | J242: Não revisado visualmente; categoria inferida pela fonte | K242: 2026-10-23T02:07:06Z | L242: 69bb511e1d0f58e14b563752441bd656 | M242: A avaliar | N242: Não
A243: UI-00242 | B243: Alimentação e Delivery | C243: Food Ordering App Design | D243: Título não exposto pela fonte | F243: https://i.pinimg.com/originals/69/fe/51/69fe51dd6778af6fd5859af92e0552c9.jpg | G243: https://www.pinterest.com/PixelFlowUI/food-ordering-app-design/ | I243: Página pública: imagem vinculada à coletânea/tópico | J243: Não revisado visualmente; categoria inferida pela fonte | K243: 2026-10-23T02:07:06Z | L243: 69fe51dd6778af6fd5859af92e0552c9 | M243: A avaliar | N243: Não
A244: UI-00243 | B244: Alimentação e Delivery | C244: Food Ordering App Design | D244: Título não exposto pela fonte | F244: https://i.pinimg.com/originals/79/27/5f/79275ffe9a1969c8963572c250c73f63.gif | G244: https://www.pinterest.com/PixelFlowUI/food-ordering-app-design/ | I244: Página pública: imagem vinculada à coletânea/tópico | J244: Não revisado visualmente; categoria inferida pela fonte | K244: 2026-10-23T02:07:06Z | L244: 79275ffe9a1969c8963572c250c73f63 | M244: A avaliar | N244: Não
... A257: UI-00256 | B257: Alimentação e Delivery | C257: Food Ordering App Design | D257: Título não exposto pela fonte | F257: https://i.pinimg.com/originals/ed/bb/12/edbb122564a05d9f495930b10ce9ae25.jpg | G257: https://www.pinterest.com/PixelFlowUI/food-ordering-app-design/ | I257: Página pública: imagem vinculada à coletânea/tópico | J257: Não revisado visualmente; categoria inferida pela fonte | K257: 2026-10-23T02:07:06Z | L257: edbb122564a05d9f495930b10ce9ae25 | M257: A avaliar | N257: Não
A258: UI-00257 | B258: Autenticação e Onboarding | C258: 3. LOGIN SCREEN | D258: Título não exposto pela fonte | F258: https://i.pinimg.com/originals/05/96/35/0596355f9811e768d0a588df299eca8a.png | G258: https://www.pinterest.com/dineshnayakdn369/3-login-screen/ | H258: 50 3. LOGIN SCREEN ideas in 2026 | mobile login, app login, login screen mobile ui | I258: Página pública: imagem vinculada à coletânea/tópico | J258: Não revisado visualmente; categoria inferida pela fonte | K258: 2026-10-23T02:06:42Z | L258: 0596355f9811e768d0a588df299eca8a | M258: A avaliar | N258: Não
A259: UI-00258 | B259: Autenticação e Onboarding | C259: 3. LOGIN SCREEN | D259: Título não exposto pela fonte | F259: https://i.pinimg.com/originals/11/e3/cd/11e3cd9bf63f42048f55a5889872d7fb.jpg | G259: https://www.pinterest.com/dineshnayakdn369/3-login-screen/ | H259: 50 3. LOGIN SCREEN ideas in 2026 | mobile login, app login, login screen mobile ui | I259: Página pública: imagem vinculada à coletânea/tópico | J259: Não revisado visualmente; categoria inferida pela fonte | K259: 2026-10-23T02:06:42Z | L259: 11e3cd9bf63f42048f55a5889872d7fb | M259: A avaliar | N259: Não
A260: UI-00259 | B260: Autenticação e Onboarding | C260: 3. LOGIN SCREEN | D260: Título não exposto pela fonte | F260: https://i.pinimg.com/originals/1d/65/ee/1d65ee0d32c33fbb138409004bd53baf.jpg | G260: https://www.pinterest.com/dineshnayakdn369/3-login-screen/ | H260: 50 3. LOGIN SCREEN ideas in 2026 | mobile login, app login, login screen mobile ui | I260: Página pública: imagem vinculada à coletânea/tópico | J260: Não revisado visualmente; categoria inferida pela fonte | K260: 2026-10-23T02:06:42Z | L260: 1d65ee0d32c33fbb138409004bd53baf | M260: A avaliar | N260: Não
A261: UI-00260 | B261: Autenticação e Onboarding | C261: 3. LOGIN SCREEN | D261: Título não exposto pela fonte | F261: https://i.pinimg.com/originals/22/21/07/2221076fb989c0bb412d40d01a5791dc.jpg | G261: https://www.pinterest.com/dineshnayakdn369/3-login-screen/ | H261: 50 3. LOGIN SCREEN ideas in 2026 | mobile login, app login, login screen mobile ui | I261: Página pública: imagem vinculada à coletânea/tópico | J261: Não revisado visualmente; categoria inferida pela fonte | K261: 2026-10-23T02:06:42Z | L261: 2221076fb989c0bb412d40d01a5791dc | M261: A avaliar | N261: Não
A262: UI-00261 | B262: Autenticação e Onboarding | C262: 3. LOGIN SCREEN | D262: Título não exposto pela fonte | F262: https://i.pinimg.com/originals/29/30/d6/2930d68c7da54629a7894ccb1149962f.png | G262: https://www.pinterest.com/dineshnayakdn369/3-login-screen/ | H262: 50 3. LOGIN SCREEN ideas in 2026 | mobile login, app login, login screen mobile ui | I262: Página pública: imagem vinculada à coletânea/tópico | J262: Não revisado visualmente; categoria inferida pela fonte | K262: 2026-10-23T02:06:42Z | L262: 2930d68c7da54629a7894ccb1149962f | M262: A avaliar | N262: Não
A263: UI-00262 | B263: Autenticação e Onboarding | C263: 3. LOGIN SCREEN | D263: Título não exposto pela fonte | F263: https://i.pinimg.com/originals/52/70/fe/5270fe6a7d099090690f12aeba20394b.jpg | G263: https://www.pinterest.com/dineshnayakdn369/3-login-screen/ | H263: 50 3. LOGIN SCREEN ideas in 2026 | mobile login, app login, login screen mobile ui | I263: Página pública: imagem vinculada à coletânea/tópico | J263: Não revisado visualmente; categoria inferida pela fonte | K263: 2026-10-23T02:06:42Z | L263: 5270fe6a7d099090690f12aeba20394b | M263: A avaliar | N263: Não
A264: UI-00263 | B264: Autenticação e Onboarding | C264: 3. LOGIN SCREEN | D264: Título não exposto pela fonte | F264: https://i.pinimg.com/originals/60/bb/b2/60bbb2da81fe0970ed012c9515a4133c.png | G264: https://www.pinterest.com/dineshnayakdn369/3-login-screen/ | H264: 50 3. LOGIN SCREEN ideas in 2026 | mobile login, app login, login screen mobile ui | I264: Página pública: imagem vinculada à coletânea/tópico | J264: Não revisado visualmente; categoria inferida pela fonte | K264: 2026-10-23T02:06:42Z | L264: 60bbb2da81fe0970ed012c9515a4133c | M264: A avaliar | N264: Não
A265: UI-00264 | B265: Autenticação e Onboarding | C265: 3. LOGIN SCREEN | D265: Título não exposto pela fonte | F265: https://i.pinimg.com/originals/6a/a0/f9/6aa0f98acf3beee79e6d107b98bafcac.jpg | G265: https://www.pinterest.com/dineshnayakdn369/3-login-screen/ | H265: 50 3. LOGIN SCREEN ideas in 2026 | mobile login, app login, login screen mobile ui | I265: Página pública: imagem vinculada à coletânea/tópico | J265: Não revisado visualmente; categoria inferida pela fonte | K265: 2026-10-23T02:06:42Z | L265: 6aa0f98acf3beee79e6d107b98bafcac | M265: A avaliar | N265: Não
A266: UI-00265 | B266: Autenticação e Onboarding | C266: 3. LOGIN SCREEN | D266: Título não exposto pela fonte | F266: https://i.pinimg.com/originals/71/dd/e0/71dde040554100f8b559ca49a651f21e.jpg | G266: https://www.pinterest.com/dineshnayakdn369/3-login-screen/ | H266: 50 3. LOGIN SCREEN ideas in 2026 | mobile login, app login, login screen mobile ui | I266: Página pública: imagem vinculada à coletânea/tópico | J266: Não revisado visualmente; categoria inferida pela fonte | K266: 2026-10-23T02:06:42Z | L266: 71dde040554100f8b559ca49a651f21e | M266: A avaliar | N266: Não
A267: UI-00266 | B267: Autenticação e Onboarding | C267: 3. LOGIN SCREEN | D267: Título não exposto pela fonte | F267: https://i.pinimg.com/originals/80/8d/ec/808decf210429b2ce48bcd866ba93a86.png | G267: https://www.pinterest.com/dineshnayakdn369/3-login-screen/ | H267: 50 3. LOGIN SCREEN ideas in 2026 | mobile login, app login, login screen mobile ui | I267: Página pública: imagem vinculada à coletânea/tópico | J267: Não revisado visualmente; categoria inferida pela fonte | K267: 2026-10-23T02:06:42Z | L267: 808decf210429b2ce48bcd866ba93a86 | M267: A avaliar | N267: Não
A268: UI-00267 | B268: Autenticação e Onboarding | C268: 3. LOGIN SCREEN | D268: Título não exposto pela fonte | F268: https://i.pinimg.com/originals/8a/ec/63/8aec6320f8f469668b0d7927edda128e.png | G268: https://www.pinterest.com/dineshnayakdn369/3-login-screen/ | H268: 50 3. LOGIN SCREEN ideas in 2026 | mobile login, app login, login screen mobile ui | I268: Página pública: imagem vinculada à coletânea/tópico | J268: Não revisado visualmente; categoria inferida pela fonte | K268: 2026-10-23T02:06:42Z | L268: 8aec6320f8f469668b0d7927edda128e | M268: A avaliar | N268: Não
A269: UI-00268 | B269: Autenticação e Onboarding | C269: 3. LOGIN SCREEN | D269: Título não exposto pela fonte | F269: https://i.pinimg.com/originals/91/00/92/910092394bb9d5f2a97d9ad367eb5131.jpg | G269: https://www.pinterest.com/dineshnayakdn369/3-login-screen/ | H269: 50 3. LOGIN SCREEN ideas in 2026 | mobile login, app login, login screen mobile ui | I269: Página pública: imagem vinculada à coletânea/tópico | J269: Não revisado visualmente; categoria inferida pela fonte | K269: 2026-10-23T02:06:42Z | L269: 910092394bb9d5f2a97d9ad367eb5131 | M269: A avaliar | N269: Não
... A405: UI-00404 | B405: UI e UX Geral | C405: designing app interface templates | D405: Título não exposto pela fonte | F405: https://i.pinimg.com/originals/e5/9b/4c/e59b4c64be8132106887c4068404b3f5.png | G405: https://www.pinterest.com/ideas/designing-app-interface-templates/954243316024/ | H405: Designing App Interface Templates | I405: Página pública: imagem vinculada à coletânea/tópico | J405: Não revisado visualmente; categoria inferida pela fonte | K405: 2026-10-23T02:06:11Z | L405: e59b4c64be8132106887c4068404b3f5 | M405: A avaliar | N405: Não
A406: UI-00405 | B406: Autenticação e Onboarding | C406: Login Design Ui App | D406: Título não exposto pela fonte | F406: https://i.pinimg.com/originals/07/13/7c/07137cac420cef1c4d249191c5156c7f.jpg | G406: https://www.pinterest.com/Modern_UI_Library/login-design-ui-app/ | I406: Página pública: imagem vinculada à coletânea/tópico | J406: Não revisado visualmente; categoria inferida pela fonte | K406: 2026-10-23T02:06:41Z | L406: 07137cac420cef1c4d249191c5156c7f | M406: A avaliar | N406: Não
A407: UI-00406 | B407: Autenticação e Onboarding | C407: Login Design Ui App | D407: Título não exposto pela fonte | F407: https://i.pinimg.com/originals/0b/fb/96/0bfb96c5e330c073b9df231df9106b96.jpg | G407: https://www.pinterest.com/Modern_UI_Library/login-design-ui-app/ | I407: Página pública: imagem vinculada à coletânea/tópico | J407: Não revisado visualmente; categoria inferida pela fonte | K407: 2026-10-23T02:06:41Z | L407: 0bfb96c5e330c073b9df231df9106b96 | M407: A avaliar | N407: Não
A408: UI-00407 | B408: Autenticação e Onboarding | C408: Login Design Ui App | D408: Título não exposto pela fonte | F408: https://i.pinimg.com/originals/18/f4/3a/18f43a7368befbf0156eb6276322aad2.jpg | G408: https://www.pinterest.com/Modern_UI_Library/login-design-ui-app/ | I408: Página pública: imagem vinculada à coletânea/tópico | J408: Não revisado visualmente; categoria inferida pela fonte | K408: 2026-10-23T02:06:41Z | L408: 18f43a7368befbf0156eb6276322aad2 | M408: A avaliar | N408: Não
A409: UI-00408 | B409: Autenticação e Onboarding | C409: Login Design Ui App | D409: Título não exposto pela fonte | F409: https://i.pinimg.com/originals/2f/1f/f3/2f1ff3eaaa47ace83d25d97987c91e32.jpg | G409: https://www.pinterest.com/Modern_UI_Library/login-design-ui-app/ | I409: Página pública: imagem vinculada à coletânea/tópico | J409: Não revisado visualmente; categoria inferida pela fonte | K409: 2026-10-23T02:06:41Z | L409: 2f1ff3eaaa47ace83d25d97987c91e32 | M409: A avaliar | N409: Não
A410: UI-00409 | B410: Autenticação e Onboarding | C410: Login Design Ui App | D410: Título não exposto pela fonte | F410: https://i.pinimg.com/originals/31/f5/b8/31f5b889152e5f41b735ba95731dc220.jpg | G410: https://www.pinterest.com/Modern_UI_Library/login-design-ui-app/ | I410: Página pública: imagem vinculada à coletânea/tópico | J410: Não revisado visualmente; categoria inferida pela fonte | K410: 2026-10-23T02:06:41Z | L410: 31f5b889152e5f41b735ba95731dc220 | M410: A avaliar | N410: Não
A411: UI-00410 | B411: Autenticação e Onboarding | C411: Login Design Ui App | D411: Título não exposto pela fonte | F411: https://i.pinimg.com/originals/3c/d4/b9/3cd4b9cbd3be608982c8977ba45bd1d3.png | G411: https://www.pinterest.com/Modern_UI_Library/login-design-ui-app/ | I411: Página pública: imagem vinculada à coletânea/tópico | J411: Não revisado visualmente; categoria inferida pela fonte | K411: 2026-10-23T02:06:41Z | L411: 3cd4b9cbd3be608982c8977ba45bd1d3 | M411: A avaliar | N411: Não
A412: UI-00411 | B412: Autenticação e Onboarding | C412: Login Design Ui App | D412: Título não exposto pela fonte | F412: https://i.pinimg.com/originals/44/ee/5d/44ee5d6fb4e05553502cd70cdac8025a.jpg | G412: https://www.pinterest.com/Modern_UI_Library/login-design-ui-app/ | I412: Página pública: imagem vinculada à coletânea/tópico | J412: Não revisado visualmente; categoria inferida pela fonte | K412: 2026-10-23T02:06:41Z | L412: 44ee5d6fb4e05553502cd70cdac8025a | M412: A avaliar | N412: Não
A413: UI-00412 | B413: Autenticação e Onboarding | C413: Login Design Ui App | D413: Título não exposto pela fonte | F413: https://i.pinimg.com/originals/54/6d/46/546d4600ba8892ad71ec8b98e756395e.jpg | G413: https://www.pinterest.com/Modern_UI_Library/login-design-ui-app/ | I413: Página pública: imagem vinculada à coletânea/tópico | J413: Não revisado visualmente; categoria inferida pela fonte | K413: 2026-10-23T02:06:41Z | L413: 546d4600ba8892ad71ec8b98e756395e | M413: A avaliar | N413: Não
A414: UI-00413 | B414: Autenticação e Onboarding | C414: Login Design Ui App | D414: Título não exposto pela fonte | F414: https://i.pinimg.com/originals/57/29/b8/5729b8c34117fbdeb53808e78808db0d.jpg | G414: https://www.pinterest.com/Modern_UI_Library/login-design-ui-app/ | I414: Página pública: imagem vinculada à coletânea/tópico | J414: Não revisado visualmente; categoria inferida pela fonte | K414: 2026-10-23T02:06:41Z | L414: 5729b8c34117fbdeb53808e78808db0d | M414: A avaliar | N414: Não
A415: UI-00414 | B415: Autenticação e Onboarding | C415: Login Design Ui App | D415: Título não exposto pela fonte | F415: https://i.pinimg.com/originals/5a/01/f1/5a01f184de153380e3f949b9d379713f.png | G415: https://www.pinterest.com/Modern_UI_Library/login-design-ui-app/ | I415: Página pública: imagem vinculada à coletânea/tópico | J415: Não revisado visualmente; categoria inferida pela fonte | K415: 2026-10-23T02:06:41Z | L415: 5a01f184de153380e3f949b9d379713f | M415: A avaliar | N415: Não
A416: UI-00415 | B416: Autenticação e Onboarding | C416: Login Design Ui App | D416: Título não exposto pela fonte | F416: https://i.pinimg.com/originals/68/29/f6/6829f62d551e15ce94809931503d89bf.png | G416: https://www.pinterest.com/Modern_UI_Library/login-design-ui-app/ | I416: Página pública: imagem vinculada à coletânea/tópico | J416: Não revisado visualmente; categoria inferida pela fonte | K416: 2026-10-23T02:06:41Z | L416: 6829f62d551e15ce94809931503d89bf | M416: A avaliar | N416: Não
A417: UI-00416 | B417: Autenticação e Onboarding | C417: Login Design Ui App | D417: Título não exposto pela fonte | F417: https://i.pinimg.com/originals/69/7f/5d/697f5df2bddaa47734b160d030838cd6.png | G417: https://www.pinterest.com/Modern_UI_Library/login-design-ui-app/ | I417: Página pública: imagem vinculada à coletânea/tópico | J417: Não revisado visualmente; categoria inferida pela fonte | K417: 2026-10-23T02:06:41Z | L417: 697f5df2bddaa47734b160d030838cd6 | M417: A avaliar | N417: Não
... A478: UI-00477 | B478: Autenticação e Onboarding | C478: Login Design Ui Website | D478: Título não exposto pela fonte | F478: https://i.pinimg.com/originals/f1/39/97/f13997dc1b118a4a59c7098b7cbc9f57.jpg | G478: https://www.pinterest.com/Modern_UI_Library/login-design-ui-website/ | I478: Página pública: imagem vinculada à coletânea/tópico | J478: Não revisado visualmente; categoria inferida pela fonte | K478: 2026-10-23T02:07:11Z | L478: f13997dc1b118a4a59c7098b7cbc9f57 | M478: A avaliar | N478: Não
A479: UI-00478 | B479: Autenticação e Onboarding | C479: ui design interface templates | D479: Título não exposto pela fonte | F479: https://i.pinimg.com/originals/03/9e/6d/039e6d86b18ed7fe742c5eec85ded30d.jpg | G479: https://www.pinterest.com/ideas/ui-design-interface-templates/910878231785/ | H479: Ui Design Interface Templates | I479: Página pública: imagem vinculada à coletânea/tópico | J479: Não revisado visualmente; categoria inferida pela fonte | K479: 2026-10-23T02:06:09Z | L479: 039e6d86b18ed7fe742c5eec85ded30d | M479: A avaliar | N479: Não
A480: UI-00479 | B480: Autenticação e Onboarding | C480: ui design interface templates | D480: Título não exposto pela fonte | F480: https://i.pinimg.com/originals/13/59/35/135935eb980a797f0f1219a48d703884.png | G480: https://www.pinterest.com/ideas/ui-design-interface-templates/910878231785/ | H480: Ui Design Interface Templates | I480: Página pública: imagem vinculada à coletânea/tópico | J480: Não revisado visualmente; categoria inferida pela fonte | K480: 2026-10-23T02:06:09Z | L480: 135935eb980a797f0f1219a48d703884 | M480: A avaliar | N480: Não
A481: UI-00480 | B481: Autenticação e Onboarding | C481: ui design interface templates | D481: Título não exposto pela fonte | F481: https://i.pinimg.com/originals/3d/a8/20/3da8201f864cdbdd1be615a3b12ae017.png | G481: https://www.pinterest.com/ideas/ui-design-interface-templates/910878231785/ | H481: Ui Design Interface Templates | I481: Página pública: imagem vinculada à coletânea/tópico | J481: Não revisado visualmente; categoria inferida pela fonte | K481: 2026-10-23T02:06:09Z | L481: 3da8201f864cdbdd1be615a3b12ae017 | M481: A avaliar | N481: Não
A482: UI-00481 | B482: Autenticação e Onboarding | C482: ui design interface templates | D482: Título não exposto pela fonte | F482: https://i.pinimg.com/originals/64/b7/d2/64b7d277f909aa5b5084805d0926f82f.jpg | G482: https://www.pinterest.com/ideas/ui-design-interface-templates/910878231785/ | H482: Ui Design Interface Templates | I482: Página pública: imagem vinculada à coletânea/tópico | J482: Não revisado visualmente; categoria inferida pela fonte | K482: 2026-10-23T02:06:09Z | L482: 64b7d277f909aa5b5084805d0926f82f | M482: A avaliar | N482: Não
A483: UI-00482 | B483: Autenticação e Onboarding | C483: ui design interface templates | D483: Título não exposto pela fonte | F483: https://i.pinimg.com/originals/82/80/31/828031286e4ac192712146a900b9018f.jpg | G483: https://www.pinterest.com/ideas/ui-design-interface-templates/910878231785/ | H483: Ui Design Interface Templates | I483: Página pública: imagem vinculada à coletânea/tópico | J483: Não revisado visualmente; categoria inferida pela fonte | K483: 2026-10-23T02:06:09Z | L483: 828031286e4ac192712146a900b9018f | M483: A avaliar | N483: Não
A484: UI-00483 | B484: Autenticação e Onboarding | C484: ui design interface templates | D484: Título não exposto pela fonte | F484: https://i.pinimg.com/originals/8b/76/8e/8b768eaf073689d0b81b54ec8cd49d8c.jpg | G484: https://www.pinterest.com/ideas/ui-design-interface-templates/910878231785/ | H484: Ui Design Interface Templates | I484: Página pública: imagem vinculada à coletânea/tópico | J484: Não revisado visualmente; categoria inferida pela fonte | K484: 2026-10-23T02:06:09Z | L484: 8b768eaf073689d0b81b54ec8cd49d8c | M484: A avaliar | N484: Não
A485: UI-00484 | B485: Autenticação e Onboarding | C485: ui design interface templates | D485: Título não exposto pela fonte | F485: https://i.pinimg.com/originals/97/c8/2d/97c82d1e2b26ffcecb53b7af0e642f9f.jpg | G485: https://www.pinterest.com/ideas/ui-design-interface-templates/910878231785/ | H485: Ui Design Interface Templates | I485: Página pública: imagem vinculada à coletânea/tópico | J485: Não revisado visualmente; categoria inferida pela fonte | K485: 2026-10-23T02:06:09Z | L485: 97c82d1e2b26ffcecb53b7af0e642f9f | M485: A avaliar | N485: Não
A486: UI-00485 | B486: Autenticação e Onboarding | C486: ui design interface templates | D486: Título não exposto pela fonte | F486: https://i.pinimg.com/originals/9a/8a/49/9a8a491cfd3174a54d159757c73d7561.jpg | G486: https://www.pinterest.com/ideas/ui-design-interface-templates/910878231785/ | H486: Ui Design Interface Templates | I486: Página pública: imagem vinculada à coletânea/tópico | J486: Não revisado visualmente; categoria inferida pela fonte | K486: 2026-10-23T02:06:09Z | L486: 9a8a491cfd3174a54d159757c73d7561 | M486: A avaliar | N486: Não
A487: UI-00486 | B487: Autenticação e Onboarding | C487: ui design interface templates | D487: Título não exposto pela fonte | F487: https://i.pinimg.com/originals/9c/e9/61/9ce96121d2cc8a344aa1286b47a45bde.jpg | G487: https://www.pinterest.com/ideas/ui-design-interface-templates/910878231785/ | H487: Ui Design Interface Templates | I487: Página pública: imagem vinculada à coletânea/tópico | J487: Não revisado visualmente; categoria inferida pela fonte | K487: 2026-10-23T02:06:09Z | L487: 9ce96121d2cc8a344aa1286b47a45bde | M487: A avaliar | N487: Não
A488: UI-00487 | B488: Autenticação e Onboarding | C488: ui design interface templates | D488: Título não exposto pela fonte | F488: https://i.pinimg.com/originals/a0/50/9b/a0509b2543468678017a2982ec93d493.png | G488: https://www.pinterest.com/ideas/ui-design-interface-templates/910878231785/ | H488: Ui Design Interface Templates | I488: Página pública: imagem vinculada à coletânea/tópico | J488: Não revisado visualmente; categoria inferida pela fonte | K488: 2026-10-23T02:06:09Z | L488: a0509b2543468678017a2982ec93d493 | M488: A avaliar | N488: Não
A489: UI-00488 | B489: Autenticação e Onboarding | C489: ui design interface templates | D489: Título não exposto pela fonte | F489: https://i.pinimg.com/originals/ad/27/61/ad27613befd292c8e06cec201af5e243.png | G489: https://www.pinterest.com/ideas/ui-design-interface-templates/910878231785/ | H489: Ui Design Interface Templates | I489: Página pública: imagem vinculada à coletânea/tópico | J489: Não revisado visualmente; categoria inferida pela fonte | K489: 2026-10-23T02:06:09Z | L489: ad27613befd292c8e06cec201af5e243 | M489: A avaliar | N489: Não
A490: UI-00489 | B490: Autenticação e Onboarding | C490: ui design interface templates | D490: Título não exposto pela fonte | F490: https://i.pinimg.com/originals/b6/b3/95/b6b39522c825cd22d816b5cbdf71d64f.png | G490: https://www.pinterest.com/ideas/ui-design-interface-templates/910878231785/ | H490: Ui Design Interface Templates | I490: Página pública: imagem vinculada à coletânea/tópico | J490: Não revisado visualmente; categoria inferida pela fonte | K490: 2026-10-23T02:06:09Z | L490: b6b39522c825cd22d816b5cbdf71d64f | M490: A avaliar | N490: Não
... A580: UI-00579 | B580: Componentes | C580: card ui design mobile | D580: Título não exposto pela fonte | F580: https://i.pinimg.com/originals/f7/5b/18/f75b18042cba6ef8f7440e6fc54fea23.jpg | G580: https://www.pinterest.com/ideas/card-ui-design-mobile/913640190578/ | H580: Card Ui Design Mobile | I580: Página pública: imagem vinculada à coletânea/tópico | J580: Não revisado visualmente; categoria inferida pela fonte | K580: 2026-10-23T02:06:53Z | L580: f75b18042cba6ef8f7440e6fc54fea23 | M580: A avaliar | N580: Não
A581: UI-00580 | B581: Componentes | C581: Figma UI Kits and WordPress Themes | D581: Título não exposto pela fonte | F581: https://i.pinimg.com/originals/01/57/67/0157670be67c601a6c77af19e9c5a81d.png | G581: https://www.pinterest.com/Crafted_Interfaces_UI/figma-ui-kits-and-wordpress-themes/ | I581: Página pública: imagem vinculada à coletânea/tópico | J581: Não revisado visualmente; categoria inferida pela fonte | K581: 2026-10-23T02:06:52Z | L581: 0157670be67c601a6c77af19e9c5a81d | M581: A avaliar | N581: Não
A582: UI-00581 | B582: Componentes | C582: Figma UI Kits and WordPress Themes | D582: Título não exposto pela fonte | F582: https://i.pinimg.com/originals/05/f4/e7/05f4e7102dd2ce354dda68a75a90f04f.jpg | G582: https://www.pinterest.com/Crafted_Interfaces_UI/figma-ui-kits-and-wordpress-themes/ | I582: Página pública: imagem vinculada à coletânea/tópico | J582: Não revisado visualmente; categoria inferida pela fonte | K582: 2026-10-23T02:06:52Z | L582: 05f4e7102dd2ce354dda68a75a90f04f | M582: A avaliar | N582: Não
A583: UI-00582 | B583: Componentes | C583: Figma UI Kits and WordPress Themes | D583: Título não exposto pela fonte | F583: https://i.pinimg.com/originals/06/4a/b5/064ab59d132530b3b10ae945b660fc3a.webp | G583: https://www.pinterest.com/Crafted_Interfaces_UI/figma-ui-kits-and-wordpress-themes/ | I583: Página pública: imagem vinculada à coletânea/tópico | J583: Não revisado visualmente; categoria inferida pela fonte | K583: 2026-10-23T02:06:52Z | L583: 064ab59d132530b3b10ae945b660fc3a | M583: A avaliar | N583: Não
A584: UI-00583 | B584: Componentes | C584: Figma UI Kits and WordPress Themes | D584: Título não exposto pela fonte | F584: https://i.pinimg.com/originals/12/d7/8d/12d78daa4df05ad815ba70a4661c57d4.png | G584: https://www.pinterest.com/Crafted_Interfaces_UI/figma-ui-kits-and-wordpress-themes/ | I584: Página pública: imagem vinculada à coletânea/tópico | J584: Não revisado visualmente; categoria inferida pela fonte | K584: 2026-10-23T02:06:52Z | L584: 12d78daa4df05ad815ba70a4661c57d4 | M584: A avaliar | N584: Não
A585: UI-00584 | B585: Componentes | C585: Figma UI Kits and WordPress Themes | D585: Título não exposto pela fonte | F585: https://i.pinimg.com/originals/1c/8a/d2/1c8ad265cc15c8bb23606d594edfb889.jpg | G585: https://www.pinterest.com/Crafted_Interfaces_UI/figma-ui-kits-and-wordpress-themes/ | I585: Página pública: imagem vinculada à coletânea/tópico | J585: Não revisado visualmente; categoria inferida pela fonte | K585: 2026-10-23T02:06:52Z | L585: 1c8ad265cc15c8bb23606d594edfb889 | M585: A avaliar | N585: Não
A586: UI-00585 | B586: Componentes | C586: Figma UI Kits and WordPress Themes | D586: Título não exposto pela fonte | F586: https://i.pinimg.com/originals/33/ec/e2/33ece2d731b0868760ef02b33152568e.webp | G586: https://www.pinterest.com/Crafted_Interfaces_UI/figma-ui-kits-and-wordpress-themes/ | I586: Página pública: imagem vinculada à coletânea/tópico | J586: Não revisado visualmente; categoria inferida pela fonte | K586: 2026-10-23T02:06:52Z | L586: 33ece2d731b0868760ef02b33152568e | M586: A avaliar | N586: Não
A587: UI-00586 | B587: Componentes | C587: Figma UI Kits and WordPress Themes | D587: Título não exposto pela fonte | F587: https://i.pinimg.com/originals/37/ef/74/37ef748e3baec85e3182ff6b5be3fa85.jpg | G587: https://www.pinterest.com/Crafted_Interfaces_UI/figma-ui-kits-and-wordpress-themes/ | I587: Página pública: imagem vinculada à coletânea/tópico | J587: Não revisado visualmente; categoria inferida pela fonte | K587: 2026-10-23T02:06:52Z | L587: 37ef748e3baec85e3182ff6b5be3fa85 | M587: A avaliar | N587: Não
A588: UI-00587 | B588: Componentes | C588: Figma UI Kits and WordPress Themes | D588: Título não exposto pela fonte | F588: https://i.pinimg.com/originals/38/c4/7f/38c47fcd42db925b608942f0041ed884.png | G588: https://www.pinterest.com/Crafted_Interfaces_UI/figma-ui-kits-and-wordpress-themes/ | I588: Página pública: imagem vinculada à coletânea/tópico | J588: Não revisado visualmente; categoria inferida pela fonte | K588: 2026-10-23T02:06:52Z | L588: 38c47fcd42db925b608942f0041ed884 | M588: A avaliar | N588: Não
A589: UI-00588 | B589: Componentes | C589: Figma UI Kits and WordPress Themes | D589: Título não exposto pela fonte | F589: https://i.pinimg.com/originals/4b/1c/78/4b1c78cca72cdde71a1af9987e0b2eb7.png | G589: https://www.pinterest.com/Crafted_Interfaces_UI/figma-ui-kits-and-wordpress-themes/ | I589: Página pública: imagem vinculada à coletânea/tópico | J589: Não revisado visualmente; categoria inferida pela fonte | K589: 2026-10-23T02:06:52Z | L589: 4b1c78cca72cdde71a1af9987e0b2eb7 | M589: A avaliar | N589: Não
A590: UI-00589 | B590: Componentes | C590: Figma UI Kits and WordPress Themes | D590: Título não exposto pela fonte | F590: https://i.pinimg.com/originals/52/bc/2c/52bc2c18e3820b5325c2ad072c4d4549.jpg | G590: https://www.pinterest.com/Crafted_Interfaces_UI/figma-ui-kits-and-wordpress-themes/ | I590: Página pública: imagem vinculada à coletânea/tópico | J590: Não revisado visualmente; categoria inferida pela fonte | K590: 2026-10-23T02:06:52Z | L590: 52bc2c18e3820b5325c2ad072c4d4549 | M590: A avaliar | N590: Não
A591: UI-00590 | B591: Componentes | C591: Figma UI Kits and WordPress Themes | D591: Título não exposto pela fonte | F591: https://i.pinimg.com/originals/5d/ae/8e/5dae8eaf9884ceb7fb9c9caa0bc9ee2c.png | G591: https://www.pinterest.com/Crafted_Interfaces_UI/figma-ui-kits-and-wordpress-themes/ | I591: Página pública: imagem vinculada à coletânea/tópico | J591: Não revisado visualmente; categoria inferida pela fonte | K591: 2026-10-23T02:06:52Z | L591: 5dae8eaf9884ceb7fb9c9caa0bc9ee2c | M591: A avaliar | N591: Não
A592: UI-00591 | B592: Componentes | C592: Figma UI Kits and WordPress Themes | D592: Título não exposto pela fonte | F592: https://i.pinimg.com/originals/70/b9/9c/70b99c0caeb73e419ad61f0b93ece1b7.png | G592: https://www.pinterest.com/Crafted_Interfaces_UI/figma-ui-kits-and-wordpress-themes/ | I592: Página pública: imagem vinculada à coletânea/tópico | J592: Não revisado visualmente; categoria inferida pela fonte | K592: 2026-10-23T02:06:52Z | L592: 70b99c0caeb73e419ad61f0b93ece1b7 | M592: A avaliar | N592: Não
... A629: UI-00628 | B629: Componentes | C629: Sketch Ui Kits | D629: Título não exposto pela fonte | F629: https://i.pinimg.com/originals/f2/47/07/f247070f2c947c65ecdfa2c22f96c2b9.jpg | G629: https://www.pinterest.com/DesignResourcesLibrary/sketch-ui-kits/ | I629: Página pública: imagem vinculada à coletânea/tópico | J629: Não revisado visualmente; categoria inferida pela fonte | K629: 2026-10-23T02:06:52Z | L629: f247070f2c947c65ecdfa2c22f96c2b9 | M629: A avaliar | N629: Não
A630: UI-00629 | B630: Componentes | C630: UI Kit Design Website | D630: Título não exposto pela fonte | F630: https://i.pinimg.com/originals/0d/40/5a/0d405a9fcf84a111f3e06490d0680763.jpg | G630: https://www.pinterest.com/componentsinterface/ui-kit-design-website/ | H630: 900+ UI Kit Design Website ideas in 2026 | user interface design, dashboard ui, mobile app ui | I630: Página pública: imagem vinculada à coletânea/tópico | J630: Não revisado visualmente; categoria inferida pela fonte | K630: 2026-10-23T02:06:35Z | L630: 0d405a9fcf84a111f3e06490d0680763 | M630: A avaliar | N630: Não
A631: UI-00630 | B631: Componentes | C631: UI Kit Design Website | D631: Título não exposto pela fonte | F631: https://i.pinimg.com/originals/0f/29/f4/0f29f453e7c0df8424b821293d397479.png | G631: https://www.pinterest.com/componentsinterface/ui-kit-design-website/ | H631: 900+ UI Kit Design Website ideas in 2026 | user interface design, dashboard ui, mobile app ui | I631: Página pública: imagem vinculada à coletânea/tópico | J631: Não revisado visualmente; categoria inferida pela fonte | K631: 2026-10-23T02:06:35Z | L631: 0f29f453e7c0df8424b821293d397479 | M631: A avaliar | N631: Não
A632: UI-00631 | B632: Componentes | C632: UI Kit Design Website | D632: Título não exposto pela fonte | F632: https://i.pinimg.com/originals/1e/29/22/1e292209d219108b6c80e0188c55da63.jpg | G632: https://www.pinterest.com/componentsinterface/ui-kit-design-website/ | H632: 900+ UI Kit Design Website ideas in 2026 | user interface design, dashboard ui, mobile app ui | I632: Página pública: imagem vinculada à coletânea/tópico | J632: Não revisado visualmente; categoria inferida pela fonte | K632: 2026-10-23T02:06:35Z | L632: 1e292209d219108b6c80e0188c55da63 | M632: A avaliar | N632: Não
A633: UI-00632 | B633: Componentes | C633: UI Kit Design Website | D633: Título não exposto pela fonte | F633: https://i.pinimg.com/originals/21/47/3e/21473e5cd72e4afb9f8a6a988d45fc9d.png | G633: https://www.pinterest.com/componentsinterface/ui-kit-design-website/ | H633: 900+ UI Kit Design Website ideas in 2026 | user interface design, dashboard ui, mobile app ui | I633: Página pública: imagem vinculada à coletânea/tópico | J633: Não revisado visualmente; categoria inferida pela fonte | K633: 2026-10-23T02:06:35Z | L633: 21473e5cd72e4afb9f8a6a988d45fc9d | M633: A avaliar | N633: Não
A634: UI-00633 | B634: Componentes | C634: UI Kit Design Website | D634: Título não exposto pela fonte | F634: https://i.pinimg.com/originals/37/8a/ac/378aacf466dd9d56881e72c381c44534.png | G634: https://www.pinterest.com/componentsinterface/ui-kit-design-website/ | H634: 900+ UI Kit Design Website ideas in 2026 | user interface design, dashboard ui, mobile app ui | I634: Página pública: imagem vinculada à coletânea/tópico | J634: Não revisado visualmente; categoria inferida pela fonte | K634: 2026-10-23T02:06:35Z | L634: 378aacf466dd9d56881e72c381c44534 | M634: A avaliar | N634: Não
A635: UI-00634 | B635: Componentes | C635: UI Kit Design Website | D635: Título não exposto pela fonte | F635: https://i.pinimg.com/originals/4a/f5/91/4af591b0d9bf67f42b07446d82dd6c1c.png | G635: https://www.pinterest.com/componentsinterface/ui-kit-design-website/ | H635: 900+ UI Kit Design Website ideas in 2026 | user interface design, dashboard ui, mobile app ui | I635: Página pública: imagem vinculada à coletânea/tópico | J635: Não revisado visualmente; categoria inferida pela fonte | K635: 2026-10-23T02:06:35Z | L635: 4af591b0d9bf67f42b07446d82dd6c1c | M635: A avaliar | N635: Não
A636: UI-00635 | B636: Componentes | C636: UI Kit Design Website | D636: Título não exposto pela fonte | F636: https://i.pinimg.com/originals/51/e5/51/51e5515c23eb06efa1adcb13537b608b.png | G636: https://www.pinterest.com/componentsinterface/ui-kit-design-website/ | H636: 900+ UI Kit Design Website ideas in 2026 | user interface design, dashboard ui, mobile app ui | I636: Página pública: imagem vinculada à coletânea/tópico | J636: Não revisado visualmente; categoria inferida pela fonte | K636: 2026-10-23T02:06:35Z | L636: 51e5515c23eb06efa1adcb13537b608b | M636: A avaliar | N636: Não
A637: UI-00636 | B637: Componentes | C637: UI Kit Design Website | D637: Título não exposto pela fonte | F637: https://i.pinimg.com/originals/58/ba/d1/58bad198e894df44383393a86a200bb0.png | G637: https://www.pinterest.com/componentsinterface/ui-kit-design-website/ | H637: 900+ UI Kit Design Website ideas in 2026 | user interface design, dashboard ui, mobile app ui | I637: Página pública: imagem vinculada à coletânea/tópico | J637: Não revisado visualmente; categoria inferida pela fonte | K637: 2026-10-23T02:06:35Z | L637: 58bad198e894df44383393a86a200bb0 | M637: A avaliar | N637: Não
A638: UI-00637 | B638: Componentes | C638: UI Kit Design Website | D638: Título não exposto pela fonte | F638: https://i.pinimg.com/originals/5c/75/57/5c755710db04761a1e30e40ed546f1bc.jpg | G638: https://www.pinterest.com/componentsinterface/ui-kit-design-website/ | H638: 900+ UI Kit Design Website ideas in 2026 | user interface design, dashboard ui, mobile app ui | I638: Página pública: imagem vinculada à coletânea/tópico | J638: Não revisado visualmente; categoria inferida pela fonte | K638: 2026-10-23T02:06:35Z | L638: 5c755710db04761a1e30e40ed546f1bc | M638: A avaliar | N638: Não
A639: UI-00638 | B639: Componentes | C639: UI Kit Design Website | D639: Título não exposto pela fonte | F639: https://i.pinimg.com/originals/65/08/bf/6508bf7490efaf01219640834119baba.jpg | G639: https://www.pinterest.com/componentsinterface/ui-kit-design-website/ | H639: 900+ UI Kit Design Website ideas in 2026 | user interface design, dashboard ui, mobile app ui | I639: Página pública: imagem vinculada à coletânea/tópico | J639: Não revisado visualmente; categoria inferida pela fonte | K639: 2026-10-23T02:06:35Z | L639: 6508bf7490efaf01219640834119baba | M639: A avaliar | N639: Não
A640: UI-00639 | B640: Componentes | C640: UI Kit Design Website | D640: Título não exposto pela fonte | F640: https://i.pinimg.com/originals/68/f2/2e/68f22ecec5efc289137bcd0b6663a961.jpg | G640: https://www.pinterest.com/componentsinterface/ui-kit-design-website/ | H640: 900+ UI Kit Design Website ideas in 2026 | user interface design, dashboard ui, mobile app ui | I640: Página pública: imagem vinculada à coletânea/tópico | J640: Não revisado visualmente; categoria inferida pela fonte | K640: 2026-10-23T02:06:35Z | L640: 68f22ecec5efc289137bcd0b6663a961 | M640: A avaliar | N640: Não
A641: UI-00640 | B641: Componentes | C641: UI Kit Design Website | D641: Título não exposto pela fonte | F641: https://i.pinimg.com/originals/69/f4/36/69f4360b0d90e5d47a8b374e2572b21e.jpg | G641: https://www.pinterest.com/componentsinterface/ui-kit-design-website/ | H641: 900+ UI Kit Design Website ideas in 2026 | user interface design, dashboard ui, mobile app ui | I641: Página pública: imagem vinculada à coletânea/tópico | J641: Não revisado visualmente; categoria inferida pela fonte | K641: 2026-10-23T02:06:35Z | L641: 69f4360b0d90e5d47a8b374e2572b21e | M641: A avaliar | N641: Não
... A723: UI-00722 | B723: Componentes | C723: UI UX Design UI Kit Mobile App | D723: Título não exposto pela fonte | F723: https://i.pinimg.com/originals/f9/0b/d7/f90bd7d3717f2e5d2db7cc2e90a75a0e.jpg | G723: https://www.pinterest.com/flow_made_simple/ui-ux-design-ui-kit-mobile-app/ | H723: 900+ UI UX Design UI Kit Mobile App ideas in 2026 | ui kit free, android app design, mobile app design inspiration | I723: Página pública: imagem vinculada à coletânea/tópico | J723: Não revisado visualmente; categoria inferida pela fonte | K723: 2026-10-23T02:07:51Z | L723: f90bd7d3717f2e5d2db7cc2e90a75a0e | M723: A avaliar | N723: Não
A724: UI-00723 | B724: CRM | C724: crm dashboard ui | D724: CMS Dashboard Design - Ashraf Hossain | E724: https://br.pinterest.com/pin/150800287512524653/ | F724: https://i.pinimg.com/236x/00/95/26/00952688e762a55eb5cc789f3f45e43f.jpg | G724: https://br.pinterest.com/search/pins/?q=crm%20dashboard%20ui | H724: crm dashboard ui | I724: Busca autenticada: metadados do cartão | J724: Não revisado visualmente | K724: 2026-10-23T01:53:11.091Z | L724: 00952688e762a55eb5cc789f3f45e43f | M724: A avaliar | N724: Não
A725: UI-00724 | B725: CRM | C725: crm dashboard ui | D725: CRM Contact List Dashboard UI Kit | E725: https://br.pinterest.com/pin/1132022056362095656/ | F725: https://i.pinimg.com/236x/03/04/c1/0304c11da25cb182c945be4348b2bce3.jpg | G725: https://br.pinterest.com/search/pins/?q=crm%20dashboard%20ui | H725: crm dashboard ui | I725: Busca autenticada: metadados do cartão | J725: Não revisado visualmente | K725: 2026-10-23T01:51:28.193Z | L725: 0304c11da25cb182c945be4348b2bce3 | M725: A avaliar | N725: Não
A726: UI-00725 | B726: CRM | C726: crm dashboard ui | D726: HR Dashboard Template | Next.js, shadcn/ui & Tailwind CSS | E726: https://br.pinterest.com/pin/742601426101904111/ | F726: https://i.pinimg.com/236x/03/34/c9/0334c95793a8535de784f1de5586f1da.jpg | G726: https://br.pinterest.com/search/pins/?q=crm%20dashboard%20ui | H726: crm dashboard ui | I726: Busca autenticada: metadados do cartão | J726: Não revisado visualmente | K726: 2026-10-23T01:53:41.387Z | L726: 0334c95793a8535de784f1de5586f1da | M726: A avaliar | N726: Não
A727: UI-00726 | B727: CRM | C727: crm dashboard ui | D727: Green Dashboard | E727: https://br.pinterest.com/pin/1147010598893586428/ | F727: https://i.pinimg.com/236x/03/f8/33/03f833fa65d3616ad5a47541874fd7e6.jpg | G727: https://br.pinterest.com/search/pins/?q=crm%20dashboard%20ui | H727: crm dashboard ui | I727: Busca autenticada: metadados do cartão | J727: Não revisado visualmente | K727: 2026-10-23T01:53:15.011Z | L727: 03f833fa65d3616ad5a47541874fd7e6 | M727: A avaliar | N727: Não
A728: UI-00727 | B728: CRM | C728: crm dashboard ui | D728: Analytics Dashboard UI Design – Automotive SaaS, CRM, Admin Panel UX/UI | E728: https://br.pinterest.com/pin/1116189088932991697/ | F728: https://i.pinimg.com/236x/04/09/98/040998411c3c84e8f40d0408f537c4cb.jpg | G728: https://br.pinterest.com/search/pins/?q=crm%20dashboard%20ui | H728: crm dashboard ui | I728: Busca autenticada: metadados do cartão | J728: Não revisado visualmente | K728: 2026-10-23T01:50:45.601Z | L728: 040998411c3c84e8f40d0408f537c4cb | M728: A avaliar | N728: Não
A729: UI-00728 | B729: CRM | C729: crm dashboard ui | D729: Revolutionize Your Learning Journey with Axiom: The Ultimate Online Education Platform | E729: https://br.pinterest.com/pin/1116189088940289053/ | F729: https://i.pinimg.com/236x/04/3c/77/043c77bddec8ac56ce85e22015717658.jpg | G729: https://br.pinterest.com/search/pins/?q=crm%20dashboard%20ui | H729: crm dashboard ui | I729: Busca autenticada: metadados do cartão | J729: Não revisado visualmente | K729: 2026-10-23T01:51:30.124Z | L729: 043c77bddec8ac56ce85e22015717658 | M729: A avaliar | N729: Não
A730: UI-00729 | B730: CRM | C730: crm dashboard ui | D730: MicroBooks - Email Marketing CRM Dashboard | E730: https://br.pinterest.com/pin/1138425612103444035/ | F730: https://i.pinimg.com/236x/05/6e/8f/056e8f6d11d6f6fb3bd90dd0aef35541.jpg | G730: https://br.pinterest.com/search/pins/?q=crm%20dashboard%20ui | H730: crm dashboard ui | I730: Busca autenticada: metadados do cartão | J730: Não revisado visualmente | K730: 2026-10-23T01:52:24.505Z | L730: 056e8f6d11d6f6fb3bd90dd0aef35541 | M730: A avaliar | N730: Não
A731: UI-00730 | B731: CRM | C731: crm dashboard ui | D731: YDSF : CRM Dashboard UI UX Design | E731: https://br.pinterest.com/pin/1147010598892161417/ | F731: https://i.pinimg.com/236x/05/86/10/058610d3b2091e438ae7bf53e636ffe2.jpg | G731: https://br.pinterest.com/search/pins/?q=crm%20dashboard%20ui | H731: crm dashboard ui | I731: Busca autenticada: metadados do cartão | J731: Não revisado visualmente | K731: 2026-10-23T01:52:21.672Z | L731: 058610d3b2091e438ae7bf53e636ffe2 | M731: A avaliar | N731: Não
...

Sheet Fontes
A1: Página de origem | B1: Nome da fonte | C1: Imagens na base | D1: Tipo
A2: https://www.pinterest.com/ideas/app-design-inspiration-for-food-apps/921185940841/ | B2: App Design Inspiration for Food Apps | C2: 5 | D2: Tópico
A3: https://www.pinterest.com/ideas/best-food-website-design/937630932982/ | B3: Best Food Website Design | C3: 20 | D3: Tópico
A4: https://www.pinterest.com/ideas/best-restaurant-website-design/929252294751/ | B4: Best Restaurant Website Design | C4: 11 | D4: Tópico
A5: https://www.pinterest.com/ideas/colorful-food-app-design/915937352116/ | B5: Colorful Food App Design | C5: 10 | D5: Tópico
A6: https://www.pinterest.com/ideas/creating-food-app-interfaces/956412553240/ | B6: Creating Food App Interfaces | C6: 17 | D6: Tópico
A7: https://www.pinterest.com/ideas/creative-food-website-design/904312477709/ | B7: Creative Food Website Design | C7: 12 | D7: Tópico
A8: https://www.pinterest.com/ideas/creative-food-website-ideas/939320384784/ | B8: Creative Food Website Ideas | C8: 10 | D8: Tópico
A9: https://www.pinterest.com/ideas/delivery-app-dashboard/917833103396/ | B9: Delivery App Dashboard | C9: 18 | D9: Tópico
A10: https://www.pinterest.com/ideas/delivery-app-design/894926856672/ | B10: Delivery App Design | C10: 7 | D10: Tópico
A11: https://www.pinterest.com/ideas/delivery-app-interface-screens/902145139687/ | B11: Delivery App Interface Screens | C11: 16 | D11: Tópico
A12: https://www.pinterest.com/ideas/dog-food-website-design/900426060729/ | B12: Dog Food Website Design | C12: 20 | D12: Tópico
A13: https://www.pinterest.com/ideas/elegant-food-website-design/944812605727/ | B13: Elegant Food Website Design | C13: 15 | D13: Tópico
... A18: https://www.pinterest.com/ideas/food-company-website-design/912251939332/ | B18: Food Company Website Design | C18: 16 | D18: Tópico
A19: https://www.pinterest.com/PixelFlowUI/food-ordering-app-design/ | C19: 25 | D19: Coletânea
A20: https://www.pinterest.com/dineshnayakdn369/3-login-screen/ | B20: 50 3. LOGIN SCREEN ideas in 2026 | mobile login, app login, login screen mobile ui | C20: 20 | D20: Coletânea
A21: https://www.pinterest.com/ideas/android-app-login-page-design/898852656520/ | B21: Android App Login Page Design | C21: 13 | D21: Tópico
A22: https://www.pinterest.com/ideas/android-login-screen/918503989029/ | B22: Android Login Screen | C22: 9 | D22: Tópico
A23: https://www.pinterest.com/ideas/android-login-ui-design/913184501673/ | B23: Android Login Ui Design | C23: 2 | D23: Tópico
A24: https://www.pinterest.com/ideas/app-design-interface/943262663655/ | B24: App Design Interface | C24: 14 | D24: Tópico
A25: https://www.pinterest.com/ideas/app-login/952290929787/ | B25: App Login | C25: 20 | D25: Tópico
A26: https://www.pinterest.com/ideas/app-login-and-register-screen/959148603178/ | B26: App Login and Register Screen | C26: 14 | D26: Tópico
A27: https://www.pinterest.com/ideas/app-login-background/915526972241/ | B27: App Login Background | C27: 18 | D27: Tópico
A28: https://www.pinterest.com/ideas/app-login-design/951776222250/ | B28: App Login Design | C28: 3 | D28: Tópico
A29: https://www.pinterest.com/ideas/app-login-interface-design/953046347611/ | B29: App Login Interface Design | C29: 8 | D29: Tópico
A30: https://www.pinterest.com/ideas/app-login-screen-design-png/931560937187/ | B30: App Login Screen Design Png | C30: 16 | D30: Tópico
A31: https://www.pinterest.com/ideas/designing-app-interface-templates/954243316024/ | B31: Designing App Interface Templates | C31: 11 | D31: Tópico
A32: https://www.pinterest.com/Modern_UI_Library/login-design-ui-app/ | C32: 25 | D32: Coletânea
A33: https://www.pinterest.com/Modern_UI_Library/login-design-ui-mobile/ | C33: 23 | D33: Coletânea
A34: https://www.pinterest.com/Modern_UI_Library/login-design-ui-website/ | C34: 25 | D34: Coletânea
A35: https://www.pinterest.com/ideas/ui-design-interface-templates/910878231785/ | B35: Ui Design Interface Templates | C35: 16 | D35: Tópico
A36: https://www.pinterest.com/ideas/app-tab-bar-interface/961291322029/ | B36: App Tab Bar Interface | C36: 19 | D36: Tópico
A37: https://www.pinterest.com/ideas/blog-card-ui-design/941570922366/ | B37: Blog Card Ui Design | C37: 16 | D37: Tópico
A38: https://www.pinterest.com/ideas/bottom-navigation-bar-component-pack/953362098637/ | B38: Bottom Navigation Bar Component Pack | C38: 16 | D38: Tópico
A39: https://www.pinterest.com/ideas/card-ui-design/897179348952/ | B39: Card Ui Design | C39: 20 | D39: Tópico
A40: https://www.pinterest.com/ideas/card-ui-design-mobile/913640190578/ | B40: Card Ui Design Mobile | C40: 15 | D40: Tópico
A41: https://www.pinterest.com/Crafted_Interfaces_UI/figma-ui-kits-and-wordpress-themes/ | C41: 24 | D41: Coletânea
A42: https://www.pinterest.com/DesignResourcesLibrary/sketch-ui-kits/ | C42: 25 | D42: Coletânea
A43: https://www.pinterest.com/componentsinterface/ui-kit-design-website/ | B43: 900+ UI Kit Design Website ideas in 2026 | user interface design, dashboard ui, mobile app ui | C43: 23 | D43: Coletânea
A44: https://www.pinterest.com/figma_flow_ux/ui-kit-in-figma/ | B44: 900+ UI kit in figma ideas in 2026 | wireframe kit, ux kits, figma plugins free | C44: 23 | D44: Coletânea
A45: https://www.pinterest.com/argentiy/ui-kits/ | B45: UI Kits | C45: 25 | D45: Coletânea
A46: https://www.pinterest.com/flow_made_simple/ui-ux-design-ui-kit-mobile-app/ | B46: 900+ UI UX Design UI Kit Mobile App ideas in 2026 | ui kit free, android app design, mobile app design inspiration | C46: 23 | D46: Coletânea
A47: https://br.pinterest.com/search/pins/?q=crm%20dashboard%20ui | B47: crm dashboard ui | C47: 356 | D47: Busca
A48: https://www.pinterest.com/aanvabo/dashboard/ | B48: 170 ideas de Dashboard en 2026 | diseño de ui, diseño de interfaz de usuario, diseño de tablero | C48: 18 | D48: Coletânea
A49: https://www.pinterest.com/adriaansendenni/dashboard-26/ | B49: 150 ideeën over Dashboard 26 in 2026 | ui ontwerp, webdesign, dashboard ui | C49: 22 | D49: Coletânea
A50: https://www.pinterest.com/Ashikasen01/dashboard-design/ | C50: 24 | D50: Coletânea
A51: https://www.pinterest.com/alexandrebally/dashboard-interface/ | B51: 85 Dashboard interface ideas in 2026 | C51: 16 | D51: Coletânea
A52: https://www.pinterest.com/abiola2341/dashboard-interface/ | B52: 34 Dashboard interface ideas in 2026 | dashboard interface, ui design dashboard, ui design web application | C52: 19 | D52: Coletânea
A53: https://br.pinterest.com/search/pins/?q=dashboard%20ui%20design | B53: dashboard ui design | C53: 27 | D53: Busca
A54: https://www.pinterest.com/AttractiveCorner/data-visualization/ | C54: 20 | D54: Coletânea
A55: https://www.pinterest.com/UIMagicS/figma-dashboard-templates/ | C55: 23 | D55: Coletânea
A56: https://www.pinterest.com/abaforceline098/kpis-dashboard/ | B56: 37 KPI's Dashboard ideas in 2026 | kpi dashboard, editable sales dashboard template, sales performance dashboard template | C56: 18 | D56: Coletânea
A57: https://www.pinterest.com/UIXMastery_Lisa/premium-dashboard-ui-kits-free-download/ | C57: 24 | D57: Coletânea
A58: https://www.pinterest.com/FigmaResourceLab/user-dashboard-ui-design-web/ | C58: 25 | D58: Coletânea
A59: https://www.pinterest.com/ideas/best-e-commerce-website-design/902324436389/ | B59: Best E Commerce Website Design | C59: 7 | D59: Tópico
A60: https://www.pinterest.com/ideas/best-web-design-for-e-commerce/957299392653/ | B60: Best Web Design for E-commerce | C60: 7 | D60: Tópico
A61: https://www.pinterest.com/ideas/creative-e-commerce-website-design/902871004734/ | B61: Creative E Commerce Website Design | C61: 8 | D61: Tópico
A62: https://www.pinterest.com/ideas/e-commerce-app-design/923334390161/ | B62: E Commerce App Design | C62: 20 | D62: Tópico
A63: https://www.pinterest.com/ideas/e-commerce-app-mobile-ui/958136335947/ | B63: E Commerce App Mobile Ui | C63: 10 | D63: Tópico
A64: https://www.pinterest.com/ideas/e-commerce-app-ui-design/905679367465/ | B64: E-commerce App Ui Design | C64: 9 | D64: Tópico
A65: https://www.pinterest.com/ideas/e-commerce-homepage-design-tips/928554515634/ | B65: E-commerce Homepage Design Tips | C65: 9 | D65: Tópico
A66: https://www.pinterest.com/ideas/e-commerce-landing-page/960907562410/ | B66: E Commerce Landing Page | C66: 7 | D66: Tópico
A67: https://www.pinterest.com/ideas/e-commerce-ui-design/903654479955/ | B67: E Commerce Ui Design | C67: 3 | D67: Tópico
A68: https://www.pinterest.com/ideas/e-commerce-web-design/928669299572/ | B68: E Commerce Web Design | C68: 7 | D68: Tópico
A69: https://www.pinterest.com/ideas/e-commerce-web-design-templates/919296658506/ | B69: E Commerce Web Design Templates | C69: 2 | D69: Tópico
A70: https://www.pinterest.com/ideas/e-commerce-website-banner-design/957567042132/ | B70: E Commerce Website Banner Design | C70: 14 | D70: Tópico
... A77: https://www.pinterest.com/ideas/e-commerce-website-setup-guide/941271773714/ | B77: E-commerce Website Setup Guide | C77: 19 | D77: Tópico
A78: https://www.pinterest.com/TheMadBrainsAIUIUXDesignStudio/ecommerce-web-design/ | C78: 17 | D78: Coletânea
A79: https://www.pinterest.com/EcommerceWebsiteTemplates/free-e-commerce-website-templates/ | C79: 25 | D79: Coletânea
A80: https://www.pinterest.com/ideas/academi-e-learning-dashboard-design/902898985960/ | B80: Academi E-learning Dashboard Design | C80: 11 | D80: Tópico
A81: https://www.pinterest.com/ideas/canvas-school-dashboard-aesthetic/921192542022/ | B81: Canvas School Dashboard Aesthetic | C81: 20 | D81: Tópico
A82: https://www.pinterest.com/ideas/colorful-educational-app-interface/913024962253/ | B82: Colorful Educational App Interface | C82: 14 | D82: Tópico
A83: https://www.pinterest.com/ideas/course-app-design/916018849924/ | B83: Course App Design | C83: 9 | D83: Tópico
A84: https://www.pinterest.com/ideas/course-card-ui-design/898265717209/ | B84: Course Card Ui Design | C84: 18 | D84: Tópico
A85: https://www.pinterest.com/ideas/course-management-dashboard/943666774771/ | B85: Course Management Dashboard | C85: 8 | D85: Tópico
A86: https://www.pinterest.com/ideas/course-website-design/926787206175/ | B86: Course Website Design | C86: 17 | D86: Tópico
A87: https://www.pinterest.com/ideas/course-website-design-inspiration/927794685985/ | B87: Course Website Design Inspiration | C87: 8 | D87: Tópico
A88: https://www.pinterest.com/ideas/e-learning-app-ui-design/920207231953/ | B88: E Learning App Ui Design | C88: 8 | D88: Tópico
A89: https://www.pinterest.com/ideas/e-learning-dashboard-design/896159589454/ | B89: E-learning Dashboard Design | C89: 8 | D89: Tópico
A90: https://www.pinterest.com/ideas/e-learning-mobile-app-design/893906630601/ | B90: E Learning Mobile App Design | C90: 13 | D90: Tópico
A91: https://www.pinterest.com/ideas/e-learning-platform-design/933154148794/ | B91: E Learning Platform Design | C91: 10 | D91: Tópico
... A108: https://www.pinterest.com/hellosomesquare/e-wallet-mobile-app-ui-design-inspiration/ | B108: 160 E wallet mobile app ui design inspiration ideas | e wallet app ui, wallet app ui, digital wallet app design | C108: 24 | D108: Coletânea
A109: https://www.pinterest.com/FigmaResourceLab/finance-dashboard-ui-design/ | C109: 25 | D109: Coletânea
A110: https://www.pinterest.com/FigmaResourceLab/finance-dashboard-ui-mobile/ | C110: 25 | D110: Coletânea
A111: https://www.pinterest.com/DonnyasPortfolio/fintech-website-ui/ | C111: 25 | D111: Coletânea
A112: https://www.pinterest.com/ideas/chatbot-interface/906264826132/ | B112: Chatbot Interface | C112: 7 | D112: Tópico
A113: https://www.pinterest.com/ideas/chatbot-ui-design/917392977700/ | B113: Chatbot Ui Design | C113: 19 | D113: Tópico
A114: https://www.pinterest.com/ideas/chatbot-ui-design-desktop/954504809789/ | B114: Chatbot Ui Design Desktop | C114: 9 | D114: Tópico
A115: https://www.pinterest.com/ideas/chatbot-ui-design-web/898716686712/ | B115: Chatbot Ui Design Web | C115: 1 | D115: Tópico
A116: https://www.pinterest.com/ideas/chatbot-ui-ux-design/915697712171/ | B116: Chatbot Ui Ux Design | C116: 2 | D116: Tópico
A117: https://www.pinterest.com/ideas/creative-chatbot-ui-design/895355272172/ | B117: Creative Chatbot Ui Design | C117: 12 | D117: Tópico
A118: https://www.pinterest.com/ideas/modern-chatbot-ui-design/959642922535/ | B118: Modern Chatbot Ui Design | C118: 5 | D118: Tópico
A119: https://www.pinterest.com/ideas/professional-chatbot-ui-design/950506079113/ | B119: Professional Chatbot Ui Design | C119: 6 | D119: Tópico
A120: https://www.pinterest.com/ideas/web-based-chatbot-ui-design/935226424102/ | B120: Web Based Chatbot Ui Design | C120: 8 | D120: Tópico
A121: https://www.pinterest.com/1daf6d4584dc085/app-homepage/ | B121: 88 个 App homepage 点子 | 餐饮, 美食, 版式 | C121: 23 | D121: Coletânea
A122: https://www.pinterest.com/ElectricVehicleLandingPage/electric-vehicle-landing-page/ | C122: 25 | D122: Coletânea
A123: https://www.pinterest.com/1realcj/fuel-website/ | B123: 23 Fuel website ideas in 2026 | global presence map design, renault branding ideas, renault twingo advertising | C123: 19 | D123: Coletânea
A124: https://www.pinterest.com/Promadarpdesign/landing-page-design-10/ | C124: 23 | D124: Coletânea
A125: https://www.pinterest.com/OpediaDesignAgency11/other-save-pin-website/ | C125: 18 | D125: Coletânea
A126: https://www.pinterest.com/TriStateTechnology/our-web-design-mobile-app-design/ | C126: 24 | D126: Coletânea
...

Sheet Metodo
A1: Critério | B1: Aplicação
A2: Unidade de referência | B2: Uma imagem distinta publicada no Pinterest, deduplicada por assinatura do arquivo.
A3: Macroáreas | B3: UI 3D, Componentes e CRM como ponto de partida; temática ampliada por domínio e padrão de interface.
A4: Classificação | B4: Automática pelo nome da coletânea, tópico ou consulta. Não equivale a revisão individual da imagem.
A5: Links de pins | B5: Preenchidos somente quando expostos pela interface. Não foram reconstruídos a partir de IDs opacos.
A6: Imagens e origem | B6: Cada registro inclui URL da imagem e a página pública ou busca que a apresentou.
A7: Títulos ausentes | B7: O Pinterest omite títulos em parte das páginas públicas. Ausências são declaradas.
A8: Deduplicação | B8: Assinatura de 32 caracteres do arquivo de imagem; diferentes tamanhos do mesmo arquivo contam uma vez.
A9: Limite da deduplicação | B9: Recortes, edições e republicações com outro arquivo podem continuar presentes. Não foi feito teste de similaridade visual.
A10: Curadoria | B10: Nenhuma alegação de melhores interfaces, acessibilidade, usabilidade ou autoria foi validada individualmente.
A11: Data de consulta | B11: 22/10/2026, America/Sao_Paulo. Carimbos de coleta individuais em UTC.
A12: Referências iniciais | B12: https://br.pinterest.com/Icaro770/ui-3d/ | https://br.pinterest.com/Icaro770/componentes/ | https://br.pinterest.com/Icaro770/crm/
... A14: Acesso | B14: Planilha criada no Drive pessoal autorizado. Não foi solicitado compartilhamento público.
